orion_itvalley/__init__.py
orion_itvalley/orionsdk.py
orion_itvalley/agents/__init__.py
orion_itvalley/agents/chatbot.py
orion_itvalley/exemplos/__init__.py
orion_itvalley/exemplos/texttospeech.py
orion_itvalley/exemplos/transcribe.py
orion_itvalley/services/__init__.py
orion_itvalley/services/texttospeech.py
orion_itvalley/services/transcriptionaudio.py
orion_itvalley-0.1.8.dist-info/licenses/LICENSE
orion_itvalley-0.1.8.dist-info/METADATA
orion_itvalley-0.1.8.dist-info/WHEEL
orion_itvalley-0.1.8.dist-info/top_level.txt
orion_itvalley-0.1.8.dist-info/RECORD
